MANIFEST.in
README.rst
setup.cfg
setup.py
is_opencensus.egg-info/PKG-INFO
is_opencensus.egg-info/SOURCES.txt
is_opencensus.egg-info/dependency_links.txt
is_opencensus.egg-info/namespace_packages.txt
is_opencensus.egg-info/requires.txt
is_opencensus.egg-info/top_level.txt
opencensus/__init__.py
opencensus/stats/__init__.py
opencensus/stats/aggregation.py
opencensus/stats/aggregation_data.py
opencensus/stats/bucket_boundaries.py
opencensus/stats/execution_context.py
opencensus/stats/measure.py
opencensus/stats/measure_to_view_map.py
opencensus/stats/measurement.py
opencensus/stats/measurement_map.py
opencensus/stats/stats.py
opencensus/stats/stats_recorder.py
opencensus/stats/view.py
opencensus/stats/view_data.py
opencensus/stats/view_manager.py
opencensus/tags/__init__.py
opencensus/tags/tag.py
opencensus/tags/tag_key.py
opencensus/tags/tag_map.py
opencensus/tags/tag_value.py
opencensus/tags/propagation/__init__.py
opencensus/tags/propagation/binary_serializer.py
opencensus/trace/__init__.py
opencensus/trace/attributes.py
opencensus/trace/attributes_helper.py
opencensus/trace/config_integration.py
opencensus/trace/execution_context.py
opencensus/trace/link.py
opencensus/trace/span.py
opencensus/trace/span_context.py
opencensus/trace/span_data.py
opencensus/trace/stack_trace.py
opencensus/trace/status.py
opencensus/trace/time_event.py
opencensus/trace/trace_options.py
opencensus/trace/tracer.py
opencensus/trace/utils.py
opencensus/trace/exporters/__init__.py
opencensus/trace/exporters/base.py
opencensus/trace/exporters/file_exporter.py
opencensus/trace/exporters/jaeger_exporter.py
opencensus/trace/exporters/logging_exporter.py
opencensus/trace/exporters/print_exporter.py
opencensus/trace/exporters/stackdriver_exporter.py
opencensus/trace/exporters/zipkin_exporter.py
opencensus/trace/exporters/gen/__init__.py
opencensus/trace/exporters/gen/jaeger/__init__.py
opencensus/trace/exporters/gen/jaeger/agent.py
opencensus/trace/exporters/gen/jaeger/jaeger.py
opencensus/trace/exporters/transports/__init__.py
opencensus/trace/exporters/transports/background_thread.py
opencensus/trace/exporters/transports/base.py
opencensus/trace/exporters/transports/sync.py
opencensus/trace/ext/__init__.py
